inverted_index/__init__.py
inverted_index/inverted_index.py
inverted_index/prompt.py
inverted_index-0.1.1.dist-info/LICENSE.txt
inverted_index-0.1.1.dist-info/METADATA
inverted_index-0.1.1.dist-info/WHEEL
inverted_index-0.1.1.dist-info/entry_points.txt
inverted_index-0.1.1.dist-info/top_level.txt
inverted_index-0.1.1.dist-info/RECORD
