Metadata-Version: 2.1
Name: inverted-index
Version: 0.1.1
Summary: Inverted Index
Home-page: https://github.com/blester125/inverted-index
Author: blester125
Author-email: blester125@gmail.com
License: MIT
Download-URL: https://github.com/blester125/inverted-index/archive/0.1.1.tar.gz
Platform: UNKNOWN
Classifier: Intended Audience :: Science/Research
Classifier: Development Status :: 3 - Alpha
Classifier: Intended Audience :: Developers
Classifier: Environment :: Console
Classifier: Topic :: Scientific/Engineering
Classifier: License :: OSI Approved :: MIT License
Classifier: Natural Language :: English
Classifier: Programming Language :: Python :: 3 :: Only
Requires-Python: >=3.6
Provides-Extra: prompt
Requires-Dist: prompt-toolkit ; extra == 'prompt'
Provides-Extra: test
Requires-Dist: pytest ; extra == 'test'
